{"timestamp": 1763008919.601894, "results": [{"symbol": "DDOG", "change_3m_pct": 53.3, "change_6m_pct": 62.72}, {"symbol": "PLTR", "change_3m_pct": 1.74, "change_6m_pct": 43.77}, {"symbol": "CAH", "change_3m_pct": 36.46, "change_6m_pct": 38.68}, {"symbol": "EA", "change_3m_pct": 12.97, "change_6m_pct": 35.84}, {"symbol": "AMAT", "change_3m_pct": 22.92, "change_6m_pct": 34.11}, {"symbol": "HPE", "change_3m_pct": 10.71, "change_6m_pct": 32.68}, {"symbol": "COR", "change_3m_pct": 23.48, "change_6m_pct": 30.75}, {"symbol": "HOLX", "change_3m_pct": 9.55, "change_6m_pct": 30.53}, {"symbol": "AAPL", "change_3m_pct": 17.59, "change_6m_pct": 28.7}, {"symbol": "WST", "change_3m_pct": 11.32, "change_6m_pct": 27.06}, {"symbol": "ABBV", "change_3m_pct": 14.77, "change_6m_pct": 26.03}, {"symbol": "EVRG", "change_3m_pct": 7.21, "change_6m_pct": 21.77}, {"symbol": "CEG", "change_3m_pct": 8.66, "change_6m_pct": 21.75}, {"symbol": "DG", "change_3m_pct": -8.6, "change_6m_pct": 21.33}, {"symbol": "ETR", "change_3m_pct": 6.92, "change_6m_pct": 20.14}, {"symbol": "ES", "change_3m_pct": 13.64, "change_6m_pct": 19.81}, {"symbol": "CBOE", "change_3m_pct": 7.05, "change_6m_pct": 18.71}, {"symbol": "DAY", "change_3m_pct": 29.17, "change_6m_pct": 16.42}, {"symbol": "MMM", "change_3m_pct": 9.72, "change_6m_pct": 14.58}, {"symbol": "XYZ", "change_3m_pct": -13.51, "change_6m_pct": 13.07}]}